cellpack-1.1.1.dist-info/METADATA
cellpack-1.1.1.dist-info/WHEEL
cellpack-1.1.1.dist-info/entry_points.txt
cellpack-1.1.1.dist-info/licenses/LICENSE
cellpack/__init__.py
cellpack/autopack/AWSHandler.py
cellpack/autopack/Analysis.py
cellpack/autopack/BaseGrid.py
cellpack/autopack/Compartment.py
cellpack/autopack/DBRecipeHandler.py
cellpack/autopack/Environment.py
cellpack/autopack/FirebaseHandler.py
cellpack/autopack/GeometryTools.py
cellpack/autopack/Gradient.py
cellpack/autopack/Graphics.py
cellpack/autopack/Grid.py
cellpack/autopack/IOutils.py
cellpack/autopack/MeshStore.py
cellpack/autopack/OutputSimularium.py
cellpack/autopack/Recipe.py
cellpack/autopack/Serializable.py
cellpack/autopack/__init__.py
cellpack/autopack/binvox_rw.py
cellpack/autopack/ingredient/Ingredient.py
cellpack/autopack/ingredient/__init__.py
cellpack/autopack/ingredient/agent.py
cellpack/autopack/ingredient/grow.py
cellpack/autopack/ingredient/multi_cylinder.py
cellpack/autopack/ingredient/multi_sphere.py
cellpack/autopack/ingredient/single_cube.py
cellpack/autopack/ingredient/single_cylinder.py
cellpack/autopack/ingredient/single_sphere.py
cellpack/autopack/ingredient/utils.py
cellpack/autopack/interface_objects/__init__.py
cellpack/autopack/interface_objects/database_ids.py
cellpack/autopack/interface_objects/default_values.py
cellpack/autopack/interface_objects/gradient_data.py
cellpack/autopack/interface_objects/ingredient_types.py
cellpack/autopack/interface_objects/meta_enum.py
cellpack/autopack/interface_objects/packed_objects.py
cellpack/autopack/interface_objects/partners.py
cellpack/autopack/interface_objects/representations.py
cellpack/autopack/ldSequence.py
cellpack/autopack/loaders/__init__.py
cellpack/autopack/loaders/analysis_config_loader.py
cellpack/autopack/loaders/config_loader.py
cellpack/autopack/loaders/migrate_v1_to_v2.py
cellpack/autopack/loaders/migrate_v2_to_v2_1.py
cellpack/autopack/loaders/recipe_loader.py
cellpack/autopack/loaders/utils.py
cellpack/autopack/loaders/v1_v2_attribute_changes.py
cellpack/autopack/octree.py
cellpack/autopack/pdb_tools/center_of_pdb.py
cellpack/autopack/pdb_tools/data.py
cellpack-1.1.1.dist-info/RECORD
