Metadata-Version: 2.1
Name: cellpack
Version: 1.1.1
Summary: algorithm to pack molecular recipes
Keywords: cellpack
Author-Email: Megan Riel-Mehan <meganr@alleninstitute.org>, Saurabh Mogre <saurabh.mogre@alleninstitute.org>, Ruge Li <ruge.li@alleninstitute.org>
License: MIT license
Classifier: Development Status :: 2 - Pre-Alpha
Classifier: Intended Audience :: Developers
Classifier: License :: OSI Approved :: MIT License
Classifier: Natural Language :: English
Classifier: Programming Language :: Python :: 3.9
Project-URL: Homepage, https://github.com/mesoscope/cellpack
Requires-Python: ==3.9.*
Requires-Dist: aicsimageio>=4.14.0
Requires-Dist: boto3>=1.35.98
Requires-Dist: deepdiff>=8.1.1
Requires-Dist: fire>=0.7.0
Requires-Dist: firebase-admin>=6.6.0
Requires-Dist: matplotlib>=3.9.4
Requires-Dist: mdutils>=1.6.0
Requires-Dist: moto>=5.0.26
Requires-Dist: numpy>=2.0.2
Requires-Dist: plotly>=5.24.1
Requires-Dist: pycollada>=0.8
Requires-Dist: pymunk>=6.10.0
Requires-Dist: python-dotenv>=1.0.1
Requires-Dist: rtree>=1.3.0
Requires-Dist: scipy>=1.13.1
Requires-Dist: simulariumio>=1.11.0
Requires-Dist: tqdm>=4.67.1
Requires-Dist: trimesh>=4.5.3
